reckit/configurator.py
reckit/logger.py
reckit/random.py
reckit/dataiterator.py
reckit/preprocessor.py
reckit/evaluator.py
reckit/sort.py
reckit/__init__.py
reckit/cython/sort.cpython-37m-x86_64-linux-gnu.so
reckit/cython/eval_matrix.cpython-37m-x86_64-linux-gnu.so
reckit/cython/random_choice.cpython-37m-x86_64-linux-gnu.so
reckit/cython/tools.cpython-37m-x86_64-linux-gnu.so
reckit/cython/__init__.py
reckit/util/decorators.py
reckit/util/tools.py
reckit/util/__init__.py
reckit/plot/style.py
reckit/plot/__init__.py
reckit-0.2.4.dist-info/top_level.txt
reckit-0.2.4.dist-info/RECORD
reckit-0.2.4.dist-info/METADATA
reckit-0.2.4.dist-info/LICENSE
reckit-0.2.4.dist-info/WHEEL
